appendorgheading/__init__.py
appendorgheading-2025.2.6.2.dist-info/LICENSE
appendorgheading-2025.2.6.2.dist-info/METADATA
appendorgheading-2025.2.6.2.dist-info/WHEEL
appendorgheading-2025.2.6.2.dist-info/entry_points.txt
appendorgheading-2025.2.6.2.dist-info/top_level.txt
appendorgheading-2025.2.6.2.dist-info/RECORD
