Metadata-Version: 2.1
Name: appendorgheading
Version: 2025.2.6.2
Summary: Append a new Org mode heading to an existing Org mode file
Home-page: https://github.com/novoid/appendorgheading
Download-URL: https://github.com/novoid/appendorgheading/zipball/master
Author: Karl Voit
Author-email: tools@Karl-Voit.at
Keywords: org mode,orgmode,CLI,logging,shell
Classifier: Programming Language :: Python :: 3 :: Only
Classifier: Development Status :: 5 - Production/Stable
Classifier: Environment :: Console
Classifier: Intended Audience :: End Users/Desktop
Classifier: License :: OSI Approved :: GNU General Public License (GPL)
Classifier: Operating System :: OS Independent
License-File: LICENSE
Requires-Dist: orgformat
